LICENSE
README.md
setup.py
backtesting_walkfoward/__init__.py
backtesting_walkfoward/backtesting.py
backtesting_walkfoward/bokeh_plot.py
backtesting_walkfoward/data_class.py
backtesting_walkfoward/download_data.py
backtesting_walkfoward/errors.py
backtesting_walkfoward/fixtures.py
backtesting_walkfoward/metrics_dataframe.py
backtesting_walkfoward/walkfoward.py
backtesting_walkfoward.egg-info/PKG-INFO
backtesting_walkfoward.egg-info/SOURCES.txt
backtesting_walkfoward.egg-info/dependency_links.txt
backtesting_walkfoward.egg-info/not-zip-safe
backtesting_walkfoward.egg-info/requires.txt
backtesting_walkfoward.egg-info/top_level.txt
backtesting_walkfoward/exemples/__init__.py
backtesting_walkfoward/exemples/exemple_backtesting_indicator/__init__.py
backtesting_walkfoward/exemples/exemple_backtesting_indicator/exemple_backtesting_indicator.py
backtesting_walkfoward/exemples/exemple_backtesting_numba/__init__.py
backtesting_walkfoward/exemples/exemple_backtesting_numba/exemple_crossover_strategy.py
backtesting_walkfoward/exemples/exemple_backtesting_numba/exemple_dict_strategy_1.py
backtesting_walkfoward/exemples/exemple_backtesting_numba/exemple_dict_strategy_2.py
backtesting_walkfoward/exemples/exemple_backtesting_proftability/__init__.py
backtesting_walkfoward/exemples/exemple_backtesting_proftability/exemple_backtesting_proftability.py
backtesting_walkfoward/exemples/exemple_backtesting_proftability/exemple_backtesting_proftability_mean_return.py
backtesting_walkfoward/exemples/exemple_backtesting_rules/__init__.py
backtesting_walkfoward/exemples/exemple_backtesting_rules/exemple_backtesting_buy_close.py
backtesting_walkfoward/exemples/exemple_backtesting_rules/exemple_backtesting_buy_enter.py
backtesting_walkfoward/exemples/exemple_backtesting_rules/exemple_backtesting_sell_close.py
backtesting_walkfoward/exemples/exemple_backtesting_strategy/__init__.py
backtesting_walkfoward/exemples/exemple_backtesting_strategy/exemple_crossover.py
backtesting_walkfoward/exemples/exemple_backtesting_strategy/exemple_crossover_empty_backtest.py
backtesting_walkfoward/exemples/exemple_backtesting_strategy/exemple_crossover_i_start.py
backtesting_walkfoward/exemples/exemple_backtesting_strategy/exemple_crossover_stop_loss_atr.py
