Metadata-Version: 2.1
Name: backtesting-walkfoward
Version: 0.2
Summary: Library to execute backtesting and walkfoward testing in financial data
Home-page: https://github.com/JoaoZati/backtesting_walkfoward
Author: João Guilherme Zati ribeiro
Author-email: joaozati@gmail.com
License:                     GNU AFFERO GENERAL PUBLIC LICENSE
Platform: UNKNOWN
Classifier: Development Status :: 2 - Pre-Alpha
Classifier: Environment :: Console
Classifier: Intended Audience :: Developers
Classifier: License :: OSI Approved :: GNU Affero General Public License v3 or later (AGPLv3+)
Classifier: Operating System :: OS Independent
Classifier: Programming Language :: Python
Classifier: Programming Language :: Python :: 3.9
Classifier: Framework :: Pytest
License-File: LICENSE
